endi_split_pdf/__init__.py
endi_split_pdf/config.py
endi_split_pdf/data_finder.py
endi_split_pdf/errors.py
endi_split_pdf/log_config.py
endi_split_pdf/section.py
endi_split_pdf/splitter.py
endi_split_pdf/utils.py
endi_split_pdf-1.0.10.data/scripts/change_code_analytique
endi_split_pdf-1.0.10.data/scripts/endi-split-pdf-page2text
endi_split_pdf-1.0.10.data/scripts/endi-split-pdf-run
endi_split_pdf-1.0.10.dist-info/LICENSE.txt
endi_split_pdf-1.0.10.dist-info/METADATA
endi_split_pdf-1.0.10.dist-info/WHEEL
endi_split_pdf-1.0.10.dist-info/top_level.txt
endi_split_pdf-1.0.10.dist-info/RECORD
