Metadata-Version: 2.1
Name: endi-split-pdf
Version: 1.0.10
Summary: Splits specific PDF files and stores the result in a custom directory layout
Home-page: UNKNOWN
Author: Arezki Feth
Author-email: tech@majerti.fr
License: UNKNOWN
Platform: UNKNOWN
Classifier: Programming Language :: Python
Classifier: License :: OSI Approved :: GNU General Public License (GPL)
Classifier: Operating System :: OS Independent
Requires-Python: >=3.6
License-File: LICENSE.txt
Requires-Dist: pyyaml
Requires-Dist: PyPDF4
Requires-Dist: mailinglogger
Provides-Extra: dev
Requires-Dist: pytest ; extra == 'dev'
